{"title":"452 Animated Porn Gifs","uid":8243249,"size":367899997,"categoryP":"porn","categoryS":"pictures","magnet":"?xt=urn:btih:14ebbe40dfcfc6b1e62061a9f7e0d6f58c15023a&amp;dn=452+Animated+Porn+Gifs&amp;tr=udp%3A%2F%2Ftracker.openbittorrent.com%3A80&amp;tr=udp%3A%2F%2Fopen.demonii.com%3A1337&amp;tr=udp%3A%2F%2Ftracker.coppersurfer.tk%3A6969&amp;tr=udp%3A%2F%2Fexodus.desync.com%3A6969","seeders":1,"leechers":0,"uploader":null,"files":452,"time":1362961388,"description":"452 Animated Porn Gifs. All kinds of stuff. \n\n\nSamples:\n &lt;a href=&quot;\nhttp://piratescreens.org/show.php/6459_tumblr-lqw8k4hl9n1qk54ddo1-.gif.html&quot; rel=&quot;nofollow&quot; target=&quot;_NEW&quot;&gt;\nhttp://piratescreens.org/show.php/6459_tumblr-lqw8k4hl9n1qk54ddo1-.gif.html&lt;/a&gt; \n &lt;a href=&quot;\nhttp://piratescreens.org/show.php/6460_tumblr-maq8pcqamq1rtk8r7o1-.gif.html&quot; rel=&quot;nofollow&quot; target=&quot;_NEW&quot;&gt;\nhttp://piratescreens.org/show.php/6460_tumblr-maq8pcqamq1rtk8r7o1-.gif.html&lt;/a&gt;\n &lt;a href=&quot;\nhttp://piratescreens.org/show.php/6461_tumblr-m6depfzatg1rvfmb3o1-.gif.html&quot; rel=&quot;nofollow&quot; target=&quot;_NEW&quot;&gt;\nhttp://piratescreens.org/show.php/6461_tumblr-m6depfzatg1rvfmb3o1-.gif.html&lt;/a&gt;\n &lt;a href=&quot;\nhttp://piratescreens.org/show.php/6462_tumblr-m9ex1fvqhr1reabb8o1-.gif.html&quot; rel=&quot;nofollow&quot; target=&quot;_NEW&quot;&gt;\nhttp://piratescreens.org/show.php/6462_tumblr-m9ex1fvqhr1reabb8o1-.gif.html&lt;/a&gt;\n &lt;a href=&quot;\nhttp://piratescreens.org/show.php/6463_tumblr-maz7lv9m9i1qfaf1fo1-.gif.html&quot; rel=&quot;nofollow&quot; target=&quot;_NEW&quot;&gt;\nhttp://piratescreens.org/show.php/6463_tumblr-maz7lv9m9i1qfaf1fo1-.gif.html&lt;/a&gt; ","torrent":{"xt":"urn:btih:14ebbe40dfcfc6b1e62061a9f7e0d6f58c15023a","amp;dn":"452+Animated+Porn+Gifs","amp;tr":["udp%3A%2F%2Ftracker.openbittorrent.com%3A80","udp%3A%2F%2Fopen.demonii.com%3A1337","udp%3A%2F%2Ftracker.coppersurfer.tk%3A6969","udp%3A%2F%2Fexodus.desync.com%3A6969"],"infoHash":"14ebbe40dfcfc6b1e62061a9f7e0d6f58c15023a","infoHashBuffer":{"type":"Buffer","data":[20,235,190,64,223,207,198,177,230,32,97,169,247,224,214,245,140,21,2,58]},"announce":[],"urlList":[]}}