{"title":"Shipping.Wars.-.Die.Transporter.S04E04.Die.Yacht.GERMAN.DOKU.SAT","uid":9238580,"size":239356552,"categoryP":"video","categoryS":"tv_shows","magnet":"?xt=urn:btih:2148add2ebbb4d3827727132117c16a7d1e79ebd&amp;dn=Shipping.Wars.-.Die.Transporter.S04E04.Die.Yacht.GERMAN.DOKU.SAT&amp;tr=udp%3A%2F%2Ftracker.openbittorrent.com%3A80&amp;tr=udp%3A%2F%2Fopen.demonii.com%3A1337&amp;tr=udp%3A%2F%2Ftracker.coppersurfer.tk%3A6969&amp;tr=udp%3A%2F%2Fexodus.desync.com%3A6969","seeders":1,"leechers":1,"uploader":"TvTeam","files":5,"time":1385226977,"description":"::::::::::::::::::::::::::::::::::::::::::::::::::::::::::::::::::::::::::\n  &lt;a href=&quot;\nhttp://www.torrenting.com&quot; rel=&quot;nofollow&quot; target=&quot;_NEW&quot;&gt;\nhttp://www.torrenting.com&lt;/a&gt;\n\nEver Experianced a perfect Scene torrent site?\n\n\n\nGive it a try: http://www.torrenting.com\n\n\n\nYou will not regret.\n\nSign up is free and open !!!\n\n\n::::::::::::::::::::::::::::::::::::::::::::::::::::::::::::::::::::::::::\n\n(= Enjoy No RAR releases =)","torrent":{"xt":"urn:btih:2148add2ebbb4d3827727132117c16a7d1e79ebd","amp;dn":"Shipping.Wars.-.Die.Transporter.S04E04.Die.Yacht.GERMAN.DOKU.SAT","amp;tr":["udp%3A%2F%2Ftracker.openbittorrent.com%3A80","udp%3A%2F%2Fopen.demonii.com%3A1337","udp%3A%2F%2Ftracker.coppersurfer.tk%3A6969","udp%3A%2F%2Fexodus.desync.com%3A6969"],"infoHash":"2148add2ebbb4d3827727132117c16a7d1e79ebd","infoHashBuffer":{"type":"Buffer","data":[33,72,173,210,235,187,77,56,39,114,113,50,17,124,22,167,209,231,158,189]},"announce":[],"urlList":[]}}