{"title":"Animals.United.2010.3D.DVDRip.XviD-EXViD","uid":6604593,"size":740896679,"categoryP":"video","categoryS":"movies","magnet":"?xt=urn:btih:33cb940b3d088d4419d9391a940fcb75e3867026&amp;dn=Animals.United.2010.3D.DVDRip.XviD-EXViD&amp;tr=udp%3A%2F%2Ftracker.openbittorrent.com%3A80&amp;tr=udp%3A%2F%2Fopen.demonii.com%3A1337&amp;tr=udp%3A%2F%2Ftracker.coppersurfer.tk%3A6969&amp;tr=udp%3A%2F%2Fexodus.desync.com%3A6969","seeders":1,"leechers":0,"uploader":".BONE.","files":3,"time":1313343806,"description":" &lt;a href=&quot;http://www.imgcrave.com/u/xzQZ8.jpg&quot; rel=&quot;nofollow&quot; target=&quot;_NEW&quot;&gt;http://www.imgcrave.com/u/xzQZ8.jpg&lt;/a&gt;\n &lt;a href=&quot;\nhttp://www.imgcrave.com/u/yjOYS.jpg&quot; rel=&quot;nofollow&quot; target=&quot;_NEW&quot;&gt;\nhttp://www.imgcrave.com/u/yjOYS.jpg&lt;/a&gt;\n &lt;a href=&quot;\nhttp://www.imgcrave.com/u/ngjZt.jpg&quot; rel=&quot;nofollow&quot; target=&quot;_NEW&quot;&gt;\nhttp://www.imgcrave.com/u/ngjZt.jpg&lt;/a&gt;","torrent":{"xt":"urn:btih:33cb940b3d088d4419d9391a940fcb75e3867026","amp;dn":"Animals.United.2010.3D.DVDRip.XviD-EXViD","amp;tr":["udp%3A%2F%2Ftracker.openbittorrent.com%3A80","udp%3A%2F%2Fopen.demonii.com%3A1337","udp%3A%2F%2Ftracker.coppersurfer.tk%3A6969","udp%3A%2F%2Fexodus.desync.com%3A6969"],"infoHash":"33cb940b3d088d4419d9391a940fcb75e3867026","infoHashBuffer":{"type":"Buffer","data":[51,203,148,11,61,8,141,68,25,217,57,26,148,15,203,117,227,134,112,38]},"announce":[],"urlList":[]}}