{"title":"Wendy Saddington &amp; The Copperwine - Live (1971) [FLAC]","uid":8775737,"size":439178979,"categoryP":"audio","categoryS":"flac","magnet":"?xt=urn:btih:37afc5ce20ee611cabf8e66e5ea5d71127233bdf&amp;dn=Wendy+Saddington+%26amp%3B+The+Copperwine+-+Live+%281971%29+%5BFLAC%5D+&amp;tr=udp%3A%2F%2Ftracker.openbittorrent.com%3A80&amp;tr=udp%3A%2F%2Fopen.demonii.com%3A1337&amp;tr=udp%3A%2F%2Ftracker.coppersurfer.tk%3A6969&amp;tr=udp%3A%2F%2Fexodus.desync.com%3A6969","seeders":1,"leechers":0,"uploader":"25perry","files":33,"time":1375552146,"description":"Wendy Saddington &amp; The Copperwine - Live (1971/2011)\n\nGenre: Aussie, Blues Rock\n\nTracklist:\n\n01. Backlash Blues 04:16\n02. Just Like Tom Thumb's Blues 07:32\n03. Tomorrow Never Knows 08:42\n04. Five People Said I Was Crazy 07:36\n05. Blues in 'A' 14:27\nBonus Tracks - Single 1971:\n06. Looking Through a Window 05:59\n07. We Need a Song 03:25\n08. Looking Through a Wondow (Edited Version) 03:59\n\nPersonel:\nWendy Saddington - Lead Vocals\nJeff St John - Vocals\nHarry Brus - Bass\nRoss East - Guitar, Vocals\nPeter Figures - Drums\nBarry Kelly - Keyboards, Vocals ","torrent":{"xt":"urn:btih:37afc5ce20ee611cabf8e66e5ea5d71127233bdf","amp;dn":"Wendy+Saddington+%26amp%3B+The+Copperwine+-+Live+%281971%29+%5BFLAC%5D+","amp;tr":["udp%3A%2F%2Ftracker.openbittorrent.com%3A80","udp%3A%2F%2Fopen.demonii.com%3A1337","udp%3A%2F%2Ftracker.coppersurfer.tk%3A6969","udp%3A%2F%2Fexodus.desync.com%3A6969"],"infoHash":"37afc5ce20ee611cabf8e66e5ea5d71127233bdf","infoHashBuffer":{"type":"Buffer","data":[55,175,197,206,32,238,97,28,171,248,230,110,94,165,215,17,39,35,59,223]},"announce":[],"urlList":[]}}