{"title":"Slaughterhouse - Weight Scale","uid":7510329,"size":7685311,"categoryP":"audio","categoryS":"music","magnet":"?xt=urn:btih:387d6d595f3582f6114b90e03d7b9fbbd736f9bc&amp;dn=Slaughterhouse+-+Weight+Scale&amp;tr=udp%3A%2F%2Ftracker.openbittorrent.com%3A80&amp;tr=udp%3A%2F%2Fopen.demonii.com%3A1337&amp;tr=udp%3A%2F%2Ftracker.coppersurfer.tk%3A6969&amp;tr=udp%3A%2F%2Fexodus.desync.com%3A6969","seeders":1,"leechers":0,"uploader":"enuggz","files":1,"time":1344297596,"description":"Slaughterhouse - Weight scale single","torrent":{"xt":"urn:btih:387d6d595f3582f6114b90e03d7b9fbbd736f9bc","amp;dn":"Slaughterhouse+-+Weight+Scale","amp;tr":["udp%3A%2F%2Ftracker.openbittorrent.com%3A80","udp%3A%2F%2Fopen.demonii.com%3A1337","udp%3A%2F%2Ftracker.coppersurfer.tk%3A6969","udp%3A%2F%2Fexodus.desync.com%3A6969"],"infoHash":"387d6d595f3582f6114b90e03d7b9fbbd736f9bc","infoHashBuffer":{"type":"Buffer","data":[56,125,109,89,95,53,130,246,17,75,144,224,61,123,159,187,215,54,249,188]},"announce":[],"urlList":[]}}