{"title":"Flags and standards of the Napoleonic Wars 1976 Keith Over","uid":13476659,"size":17634772,"categoryP":"other","categoryS":"e_books","magnet":"?xt=urn:btih:3a0ba6c7c1fe9f0e2561eaed800d939c08a30bf0&amp;dn=Flags+and+standards+of+the+Napoleonic+Wars+1976+Keith+Over&amp;tr=udp%3A%2F%2Ftracker.leechers-paradise.org%3A6969&amp;tr=udp%3A%2F%2Fzer0day.ch%3A1337&amp;tr=udp%3A%2F%2Fopen.demonii.com%3A1337&amp;tr=udp%3A%2F%2Ftracker.coppersurfer.tk%3A6969&amp;tr=udp%3A%2F%2Fexodus.desync.com%3A6969","seeders":1,"leechers":0,"uploader":"Horisarte","files":1,"time":1455016890,"description":"http://www.abebooks.co.uk/Flags-Standards-Napoleonic-Wars-Over-Keith/723477848/bd","torrent":{"xt":"urn:btih:3a0ba6c7c1fe9f0e2561eaed800d939c08a30bf0","amp;dn":"Flags+and+standards+of+the+Napoleonic+Wars+1976+Keith+Over","amp;tr":["udp%3A%2F%2Ftracker.leechers-paradise.org%3A6969","udp%3A%2F%2Fzer0day.ch%3A1337","udp%3A%2F%2Fopen.demonii.com%3A1337","udp%3A%2F%2Ftracker.coppersurfer.tk%3A6969","udp%3A%2F%2Fexodus.desync.com%3A6969"],"infoHash":"3a0ba6c7c1fe9f0e2561eaed800d939c08a30bf0","infoHashBuffer":{"type":"Buffer","data":[58,11,166,199,193,254,159,14,37,97,234,237,128,13,147,156,8,163,11,240]},"announce":[],"urlList":[]}}