{"title":"WiredPussy - Lorelei Lee, Melissa Jacobs","uid":6794294,"size":2472495035,"categoryP":"porn","categoryS":"movies","magnet":"?xt=urn:btih:487cca5edd5c69115bc36f9fb8512a4307f95746&amp;dn=WiredPussy+-+Lorelei+Lee%2C+Melissa+Jacobs&amp;tr=udp%3A%2F%2Ftracker.openbittorrent.com%3A80&amp;tr=udp%3A%2F%2Fopen.demonii.com%3A1337&amp;tr=udp%3A%2F%2Ftracker.coppersurfer.tk%3A6969&amp;tr=udp%3A%2F%2Fexodus.desync.com%3A6969","seeders":1,"leechers":0,"uploader":"exmnova","files":1,"time":1320391663,"description":"[WiredPussy - Lorelei Lee, Melissa Jacobs\n\n &lt;a href=&quot;\nhttp://0.picswan.com/show.php/22789_2.jpg.html&quot; rel=&quot;nofollow&quot; target=&quot;_NEW&quot;&gt;\nhttp://0.picswan.com/show.php/22789_2.jpg.html&lt;/a&gt;\n &lt;a href=&quot;\nhttp://0.picswan.com/show.php/22788_1.jpg.html&quot; rel=&quot;nofollow&quot; target=&quot;_NEW&quot;&gt;\nhttp://0.picswan.com/show.php/22788_1.jpg.html&lt;/a&gt;\n","torrent":{"xt":"urn:btih:487cca5edd5c69115bc36f9fb8512a4307f95746","amp;dn":"WiredPussy+-+Lorelei+Lee%2C+Melissa+Jacobs","amp;tr":["udp%3A%2F%2Ftracker.openbittorrent.com%3A80","udp%3A%2F%2Fopen.demonii.com%3A1337","udp%3A%2F%2Ftracker.coppersurfer.tk%3A6969","udp%3A%2F%2Fexodus.desync.com%3A6969"],"infoHash":"487cca5edd5c69115bc36f9fb8512a4307f95746","infoHashBuffer":{"type":"Buffer","data":[72,124,202,94,221,92,105,17,91,195,111,159,184,81,42,67,7,249,87,70]},"announce":[],"urlList":[]}}