{"title":"Ruffride - 2Deep (Studio Mix) June 6th 2009","uid":4965688,"size":191471389,"categoryP":"audio","categoryS":"music","magnet":"?xt=urn:btih:5426cb009b130692eda2cb1ffad0c06d4bcc03c1&amp;dn=Ruffride+-+2Deep+%28Studio+Mix%29+June+6th+2009&amp;tr=udp%3A%2F%2Ftracker.openbittorrent.com%3A80&amp;tr=udp%3A%2F%2Fopen.demonii.com%3A1337&amp;tr=udp%3A%2F%2Ftracker.coppersurfer.tk%3A6969&amp;tr=udp%3A%2F%2Fexodus.desync.com%3A6969","seeders":1,"leechers":0,"uploader":"L.dub","files":1,"time":1245521678,"description":"Ruffride - 2Deep (Studio Mix) June 6th 2009\n\n\nDNB, DEEP, SOULFUL, SMOOTH, TOUCHING, ROLLING, LIQUID, CHILL, POSITIVE VIBE, UPLIFTING, SUMMER TIME, HARMONIC, LOVERS\n\n\nFacing Jinx - I Know \nDonnie Dubson - Lines To Draw\nLenzman - Caught Up\nCommand Strange - Despite Everything\nFacing Jinx - Break Out\nDonnie Dubson - You Dont Deserve Me\nAutumn - It's Always About the Girl \nLenzman - Last Day On Earth\nElement - Lost And Alone\nApex - Weeping Willow\nStunna &amp; Peyo - Do U Remember\nDonnie Dubson - Goonies\nLenzman - The Blues\nCommand Strange - She Don't Understand\nDonnie Dubson - Everywhere\nLenzman &amp; Submorphics - Way Back When\nZero T feat. Steo - Refusal (Calibre Remix)\nDonnie Dubson - Beyond Infinity\nLenzman - Bright Lights\nLondon Elektricity - Just One Second (Apex Remix)\nHoldTight - Girl Next Door\nAlix Perez - Magnolias\nCommand Strange - In My Heart\nBachelors Of Science - The Ice Dance\n\n\nTime: 1:19:46\n\n\nwww.DnbRadio.com\n\n\nOther mix:\n &lt;a href=&quot;\nhttp://thepiratebay.se/torrent/4944814/Ruffride_-_Deep_(Studio_Mix)_June_3rd_2009&quot; rel=&quot;nofollow&quot; target=&quot;_NEW&quot;&gt;\nhttp://thepiratebay.se/torrent/4944814/Ruffride_-_Deep_(Studio_Mix)_June_3rd_2009&lt;/a&gt;\n &lt;a href=&quot;\nhttp://thepiratebay.se/torrent/5048963/Ruffride_-_Soul_Soul_Deep_(Studio_Mix)_June_30th_2009&quot; rel=&quot;nofollow&quot; target=&quot;_NEW&quot;&gt;\nhttp://thepiratebay.se/torrent/5048963/Ruffride_-_Soul_Soul_Deep_(Studio_Mix)_June_30th_2009&lt;/a&gt;\n &lt;a href=&quot;\nhttp://thepiratebay.se/torrent/3522617/Ruffride_(Can.)_-_Oldskool_Jungle_mix_(2006)&quot; rel=&quot;nofollow&quot; target=&quot;_NEW&quot;&gt;\nhttp://thepiratebay.se/torrent/3522617/Ruffride_(Can.)_-_Oldskool_Jungle_mix_(2006)&lt;/a&gt;","torrent":{"xt":"urn:btih:5426cb009b130692eda2cb1ffad0c06d4bcc03c1","amp;dn":"Ruffride+-+2Deep+%28Studio+Mix%29+June+6th+2009","amp;tr":["udp%3A%2F%2Ftracker.openbittorrent.com%3A80","udp%3A%2F%2Fopen.demonii.com%3A1337","udp%3A%2F%2Ftracker.coppersurfer.tk%3A6969","udp%3A%2F%2Fexodus.desync.com%3A6969"],"infoHash":"5426cb009b130692eda2cb1ffad0c06d4bcc03c1","infoHashBuffer":{"type":"Buffer","data":[84,38,203,0,155,19,6,146,237,162,203,31,250,208,192,109,75,204,3,193]},"announce":[],"urlList":[]}}