{"title":"EQ-137 Various actress JAV CENSORED","uid":8888885,"size":2348092256,"categoryP":"porn","categoryS":"movie_clips","magnet":"?xt=urn:btih:649512129b02a923dfe692ffacd39221e2556d85&amp;dn=EQ-137+Various+actress+JAV+CENSORED&amp;tr=udp%3A%2F%2Ftracker.openbittorrent.com%3A80&amp;tr=udp%3A%2F%2Fopen.demonii.com%3A1337&amp;tr=udp%3A%2F%2Ftracker.coppersurfer.tk%3A6969&amp;tr=udp%3A%2F%2Fexodus.desync.com%3A6969","seeders":1,"leechers":0,"uploader":"3xplanet","files":2,"time":1378534306,"description":"EQ-137 Various actress JAV CENSORED\nCover &lt;a href=&quot;\nhttp://3xplanet.com/view/9471.1378468110.JPG&quot; rel=&quot;nofollow&quot; target=&quot;_NEW&quot;&gt;\nhttp://3xplanet.com/view/9471.1378468110.JPG&lt;/a&gt;\nScreenshot &lt;a href=&quot;\nhttp://3xplanet.com/view/9514.1378468393.JPG&quot; rel=&quot;nofollow&quot; target=&quot;_NEW&quot;&gt;\nhttp://3xplanet.com/view/9514.1378468393.JPG&lt;/a&gt; &lt;a href=&quot;\nhttp://3xplanet.com/view/9547.1378468621.JPG&quot; rel=&quot;nofollow&quot; target=&quot;_NEW&quot;&gt;\nhttp://3xplanet.com/view/9547.1378468621.JPG&lt;/a&gt;\n\nTitle: full erection Este of darkness operating\nStarring: Various actress\nStudio: Brit\n\nTag: JAV, CENSORED, Brit, Massage, handjob\n\n","torrent":{"xt":"urn:btih:649512129b02a923dfe692ffacd39221e2556d85","amp;dn":"EQ-137+Various+actress+JAV+CENSORED","amp;tr":["udp%3A%2F%2Ftracker.openbittorrent.com%3A80","udp%3A%2F%2Fopen.demonii.com%3A1337","udp%3A%2F%2Ftracker.coppersurfer.tk%3A6969","udp%3A%2F%2Fexodus.desync.com%3A6969"],"infoHash":"649512129b02a923dfe692ffacd39221e2556d85","infoHashBuffer":{"type":"Buffer","data":[100,149,18,18,155,2,169,35,223,230,146,255,172,211,146,33,226,85,109,133]},"announce":[],"urlList":[]}}