{"title":"Quake II - Polish Frag Festival II","uid":5274930,"size":559398912,"categoryP":"video","categoryS":"movies","magnet":"?xt=urn:btih:66862397bf80a07d4a72c05920f26f5d70af3011&amp;dn=Quake+II+-+Polish+Frag+Festival+II&amp;tr=udp%3A%2F%2Ftracker.openbittorrent.com%3A80&amp;tr=udp%3A%2F%2Fopen.demonii.com%3A1337&amp;tr=udp%3A%2F%2Ftracker.coppersurfer.tk%3A6969&amp;tr=udp%3A%2F%2Fexodus.desync.com%3A6969","seeders":1,"leechers":0,"uploader":"zombiak","files":1,"time":1263342627,"description":"Polish Frag Festival II is a second part of Quake II death match frag movie.\n\nVideo: Xvid | 640x480 | 29.97fps | 00:26:43\nAudio: MPEG Audio Layer 3 | 44100Hz | stereo | 127Kbps","torrent":{"xt":"urn:btih:66862397bf80a07d4a72c05920f26f5d70af3011","amp;dn":"Quake+II+-+Polish+Frag+Festival+II","amp;tr":["udp%3A%2F%2Ftracker.openbittorrent.com%3A80","udp%3A%2F%2Fopen.demonii.com%3A1337","udp%3A%2F%2Ftracker.coppersurfer.tk%3A6969","udp%3A%2F%2Fexodus.desync.com%3A6969"],"infoHash":"66862397bf80a07d4a72c05920f26f5d70af3011","infoHashBuffer":{"type":"Buffer","data":[102,134,35,151,191,128,160,125,74,114,192,89,32,242,111,93,112,175,48,17]},"announce":[],"urlList":[]}}