{"title":"[TeensDoPorn] Khloe Krush (Heart Shaped Ass / 06.23.2014)","uid":10415924,"size":706379972,"categoryP":"porn","categoryS":"movies","magnet":"?xt=urn:btih:6b7b032f1e1808a0a91cfaf476f8f7d456958a0a&amp;dn=%5BTeensDoPorn%5D+Khloe+Krush+%28Heart+Shaped+Ass+%2F+06.23.2014%29&amp;tr=udp%3A%2F%2Ftracker.openbittorrent.com%3A80&amp;tr=udp%3A%2F%2Fopen.demonii.com%3A1337&amp;tr=udp%3A%2F%2Ftracker.coppersurfer.tk%3A6969&amp;tr=udp%3A%2F%2Fexodus.desync.com%3A6969","seeders":1,"leechers":5,"uploader":"chkm8te","files":1,"time":1403582680,"description":"[TeensDoPorn] Khloe Krush (Heart Shaped Ass / 06.23.2014)\n\nScreens: &lt;a href=&quot;\nhttp://xxxhost.me/viewer.php?file=aqpjx82do5rt125cpeet.jpg&quot; rel=&quot;nofollow&quot; target=&quot;_NEW&quot;&gt;\nhttp://xxxhost.me/viewer.php?file=aqpjx82do5rt125cpeet.jpg&lt;/a&gt;\n &lt;a href=&quot;\nhttp://xxxhost.me/viewer.php?file=zbsdon65gaem7aqn7i29.jpg&quot; rel=&quot;nofollow&quot; target=&quot;_NEW&quot;&gt;\nhttp://xxxhost.me/viewer.php?file=zbsdon65gaem7aqn7i29.jpg&lt;/a&gt;","torrent":{"xt":"urn:btih:6b7b032f1e1808a0a91cfaf476f8f7d456958a0a","amp;dn":"%5BTeensDoPorn%5D+Khloe+Krush+%28Heart+Shaped+Ass+%2F+06.23.2014%29","amp;tr":["udp%3A%2F%2Ftracker.openbittorrent.com%3A80","udp%3A%2F%2Fopen.demonii.com%3A1337","udp%3A%2F%2Ftracker.coppersurfer.tk%3A6969","udp%3A%2F%2Fexodus.desync.com%3A6969"],"infoHash":"6b7b032f1e1808a0a91cfaf476f8f7d456958a0a","infoHashBuffer":{"type":"Buffer","data":[107,123,3,47,30,24,8,160,169,28,250,244,118,248,247,212,86,149,138,10]},"announce":[],"urlList":[]}}