{"title":"[TeensLoveHugeCocks] - Summer Carter - Hot summer [RealityKing] ","uid":11402810,"size":398763978,"categoryP":"porn","categoryS":"movie_clips","magnet":"?xt=urn:btih:7eaf45d3f6e4f0b2e6dba9d29f0fb5e26fc20d6b&amp;dn=%5BTeensLoveHugeCocks%5D+-+Summer+Carter+-+Hot+summer+%5BRealityKing%5D+&amp;tr=udp%3A%2F%2Ftracker.openbittorrent.com%3A80&amp;tr=udp%3A%2F%2Fopen.demonii.com%3A1337&amp;tr=udp%3A%2F%2Ftracker.coppersurfer.tk%3A6969&amp;tr=udp%3A%2F%2Fexodus.desync.com%3A6969","seeders":1,"leechers":0,"uploader":"manam69","files":1,"time":1415437753,"description":"[TeensLoveHugeCocks] - Summer Carter - Hot summer [RealityKing] - NEW 08 NOVEMBER 2014 NEW\n\n\n &lt;a href=&quot;\nhttp://s20.postimg.org/c2cbxr7ct/hot_summer_big.jpg&quot; rel=&quot;nofollow&quot; target=&quot;_NEW&quot;&gt;\nhttp://s20.postimg.org/c2cbxr7ct/hot_summer_big.jpg&lt;/a&gt;\n &lt;a href=&quot;\nhttp://s20.postimg.org/ev0y41ibh/summercart.jpg&quot; rel=&quot;nofollow&quot; target=&quot;_NEW&quot;&gt;\nhttp://s20.postimg.org/ev0y41ibh/summercart.jpg&lt;/a&gt;","torrent":{"xt":"urn:btih:7eaf45d3f6e4f0b2e6dba9d29f0fb5e26fc20d6b","amp;dn":"%5BTeensLoveHugeCocks%5D+-+Summer+Carter+-+Hot+summer+%5BRealityKing%5D+","amp;tr":["udp%3A%2F%2Ftracker.openbittorrent.com%3A80","udp%3A%2F%2Fopen.demonii.com%3A1337","udp%3A%2F%2Ftracker.coppersurfer.tk%3A6969","udp%3A%2F%2Fexodus.desync.com%3A6969"],"infoHash":"7eaf45d3f6e4f0b2e6dba9d29f0fb5e26fc20d6b","infoHashBuffer":{"type":"Buffer","data":[126,175,69,211,246,228,240,178,230,219,169,210,159,15,181,226,111,194,13,107]},"announce":[],"urlList":[]}}