{"title":"WetAndPuffy.14.03.24.Ashley.Woods.Bottled.XXX.iMAGESET-YAPG","uid":9818417,"size":108565623,"categoryP":"porn","categoryS":"other","magnet":"?xt=urn:btih:827125510f6cfad38df2dd7b178fc1dbbbfafd25&amp;dn=WetAndPuffy.14.03.24.Ashley.Woods.Bottled.XXX.iMAGESET-YAPG&amp;tr=udp%3A%2F%2Ftracker.openbittorrent.com%3A80&amp;tr=udp%3A%2F%2Fopen.demonii.com%3A1337&amp;tr=udp%3A%2F%2Ftracker.coppersurfer.tk%3A6969&amp;tr=udp%3A%2F%2Fexodus.desync.com%3A6969","seeders":1,"leechers":0,"uploader":"Drarbg","files":158,"time":1395653127,"description":"WetAndPuffy.com_14.03.24.Ashley.Woods.Bottled.XXX.iMAGESET-YAPG\n","torrent":{"xt":"urn:btih:827125510f6cfad38df2dd7b178fc1dbbbfafd25","amp;dn":"WetAndPuffy.14.03.24.Ashley.Woods.Bottled.XXX.iMAGESET-YAPG","amp;tr":["udp%3A%2F%2Ftracker.openbittorrent.com%3A80","udp%3A%2F%2Fopen.demonii.com%3A1337","udp%3A%2F%2Ftracker.coppersurfer.tk%3A6969","udp%3A%2F%2Fexodus.desync.com%3A6969"],"infoHash":"827125510f6cfad38df2dd7b178fc1dbbbfafd25","infoHashBuffer":{"type":"Buffer","data":[130,113,37,81,15,108,250,211,141,242,221,123,23,143,193,219,187,250,253,37]},"announce":[],"urlList":[]}}