{"title":"Erotissimo (Jean Yanne, Francis Blanche, Annie Girardot)","uid":14260275,"size":734076968,"categoryP":"video","categoryS":"movies","magnet":"?xt=urn:btih:85fc3b574811df5348b34b5869fd1a5dae207af7&amp;dn=Erotissimo+%28Jean+Yanne%2C+Francis+Blanche%2C+Annie+Girardot%29&amp;tr=udp%3A%2F%2Ftracker.leechers-paradise.org%3A6969&amp;tr=udp%3A%2F%2Fzer0day.ch%3A1337&amp;tr=udp%3A%2F%2Fopen.demonii.com%3A1337&amp;tr=udp%3A%2F%2Ftracker.coppersurfer.tk%3A6969&amp;tr=udp%3A%2F%2Fexodus.desync.com%3A6969","seeders":1,"leechers":0,"uploader":"kilbilou","files":1,"time":1460242716,"description":"http://image.noelshack.com/fichiers/2016/14/1460235482-1.jpg\r\n\r\n\r\nOrigine du film : Français, Italien\r\nRéalisateur : Gérard Pirès\r\nActeurs : Annie Girardot, Jean Yanne, Francis Blanche\r\nGenre : Comédie\r\nDate de sortie : 18 février 2003\r\nAnnée de production : 1969\r\nNote spectateurs :  2,4/5 (40)\r\n\r\n\r\n\r\nLa riche épouse d'un PDG apprend dans un magazine que la femme moderne doit être &quot;érotique&quot;. Elle décide donc de devenir comme toutes ces filles que l'on voit sur les affiches. Son mari ne remarque pas le changement car trop occupé par un contrôle fiscal","torrent":{"xt":"urn:btih:85fc3b574811df5348b34b5869fd1a5dae207af7","amp;dn":"Erotissimo+%28Jean+Yanne%2C+Francis+Blanche%2C+Annie+Girardot%29","amp;tr":["udp%3A%2F%2Ftracker.leechers-paradise.org%3A6969","udp%3A%2F%2Fzer0day.ch%3A1337","udp%3A%2F%2Fopen.demonii.com%3A1337","udp%3A%2F%2Ftracker.coppersurfer.tk%3A6969","udp%3A%2F%2Fexodus.desync.com%3A6969"],"infoHash":"85fc3b574811df5348b34b5869fd1a5dae207af7","infoHashBuffer":{"type":"Buffer","data":[133,252,59,87,72,17,223,83,72,179,75,88,105,253,26,93,174,32,122,247]},"announce":[],"urlList":[]}}