{"title":"Barely Legal POV 16 - Staci Silverstone.mp4","uid":10705209,"size":324961351,"categoryP":"porn","categoryS":"movie_clips","magnet":"?xt=urn:btih:86c32be1798af6b30b88c0f9e7077ef246aa746c&amp;dn=Barely+Legal+POV+16+-+Staci+Silverstone.mp4&amp;tr=udp%3A%2F%2Ftracker.openbittorrent.com%3A80&amp;tr=udp%3A%2F%2Fopen.demonii.com%3A1337&amp;tr=udp%3A%2F%2Ftracker.coppersurfer.tk%3A6969&amp;tr=udp%3A%2F%2Fexodus.desync.com%3A6969","seeders":1,"leechers":5,"uploader":"Pornmaze","files":-1,"time":1407278012,"description":"Barely Legal POV 16 - Staci Silverstone.mp4\n\n2014, All Sex, Oral, Teen, POV, Swallow, Hardcore, MILF, XXX, Adult\n\n960 x 540\n\n00:27:01\n\n309.91 MB \n\nScreens\n &lt;a href=&quot;\nhttp://pixsor.com/share-5005_53E13F37.html&quot; rel=&quot;nofollow&quot; target=&quot;_NEW&quot;&gt;\nhttp://pixsor.com/share-5005_53E13F37.html&lt;/a&gt;\n &lt;a href=&quot;\nhttp://pixsor.com/share-47B1_53E13F37.html&quot; rel=&quot;nofollow&quot; target=&quot;_NEW&quot;&gt;\nhttp://pixsor.com/share-47B1_53E13F37.html&lt;/a&gt;","torrent":{"xt":"urn:btih:86c32be1798af6b30b88c0f9e7077ef246aa746c","amp;dn":"Barely+Legal+POV+16+-+Staci+Silverstone.mp4","amp;tr":["udp%3A%2F%2Ftracker.openbittorrent.com%3A80","udp%3A%2F%2Fopen.demonii.com%3A1337","udp%3A%2F%2Ftracker.coppersurfer.tk%3A6969","udp%3A%2F%2Fexodus.desync.com%3A6969"],"infoHash":"86c32be1798af6b30b88c0f9e7077ef246aa746c","infoHashBuffer":{"type":"Buffer","data":[134,195,43,225,121,138,246,179,11,136,192,249,231,7,126,242,70,170,116,108]},"announce":[],"urlList":[]}}