{"title":"Peter Vesth - Endelig Jul","uid":4540722,"size":65992059,"categoryP":"audio","categoryS":"music","magnet":"?xt=urn:btih:87625f5dfa279f395ec51824890c2af34d65c794&amp;dn=Peter+Vesth+-+Endelig+Jul&amp;tr=udp%3A%2F%2Ftracker.openbittorrent.com%3A80&amp;tr=udp%3A%2F%2Fopen.demonii.com%3A1337&amp;tr=udp%3A%2F%2Ftracker.coppersurfer.tk%3A6969&amp;tr=udp%3A%2F%2Fexodus.desync.com%3A6969","seeders":1,"leechers":0,"uploader":"labce","files":18,"time":1227931379,"description":"lidt jule musik fra bornholm","torrent":{"xt":"urn:btih:87625f5dfa279f395ec51824890c2af34d65c794","amp;dn":"Peter+Vesth+-+Endelig+Jul","amp;tr":["udp%3A%2F%2Ftracker.openbittorrent.com%3A80","udp%3A%2F%2Fopen.demonii.com%3A1337","udp%3A%2F%2Ftracker.coppersurfer.tk%3A6969","udp%3A%2F%2Fexodus.desync.com%3A6969"],"infoHash":"87625f5dfa279f395ec51824890c2af34d65c794","infoHashBuffer":{"type":"Buffer","data":[135,98,95,93,250,39,159,57,94,197,24,36,137,12,42,243,77,101,199,148]},"announce":[],"urlList":[]}}