{"title":"Shemale - Morgan Bailey - Valetines Sex.avi","uid":13751607,"size":435105352,"categoryP":"porn","categoryS":"movie_clips","magnet":"?xt=urn:btih:9d5ca0ddc9bf52d88b1a19657b337c50a0ab3537&amp;dn=Shemale+-+Morgan+Bailey+-+Valetines+Sex.avi&amp;tr=udp%3A%2F%2Ftracker.leechers-paradise.org%3A6969&amp;tr=udp%3A%2F%2Fzer0day.ch%3A1337&amp;tr=udp%3A%2F%2Fopen.demonii.com%3A1337&amp;tr=udp%3A%2F%2Ftracker.coppersurfer.tk%3A6969&amp;tr=udp%3A%2F%2Fexodus.desync.com%3A6969","seeders":1,"leechers":0,"uploader":"ibxxxxxxxxxx","files":1,"time":1457161297,"description":"Shemale - Morgan Bailey - Valetines Sex.avi\r\n\r\n\r\n\r\nHot Shemale Action\r\n\r\n\r\n\r\nReleased: 2012\r\n25 Minutes\r\n1280 x 720\r\n\r\n\r\n\r\nMessage Me if the File Needs to be Re-Seeded\r\n\r\nPlease Keep Seeding after Download\r\n\r\n\r\n\r\nStarring\r\n\r\nMorgan Bailey  \nhttp://postimg.org/image/x81es1s71/\r\n\r\n\r\n\r\nComplete Set of Screenshots \nhttp://postimg.org/gallery/s6i0uv9a/\r\n\r\n\r\n\r\n\r\nHappy Wanking","torrent":{"xt":"urn:btih:9d5ca0ddc9bf52d88b1a19657b337c50a0ab3537","amp;dn":"Shemale+-+Morgan+Bailey+-+Valetines+Sex.avi","amp;tr":["udp%3A%2F%2Ftracker.leechers-paradise.org%3A6969","udp%3A%2F%2Fzer0day.ch%3A1337","udp%3A%2F%2Fopen.demonii.com%3A1337","udp%3A%2F%2Ftracker.coppersurfer.tk%3A6969","udp%3A%2F%2Fexodus.desync.com%3A6969"],"infoHash":"9d5ca0ddc9bf52d88b1a19657b337c50a0ab3537","infoHashBuffer":{"type":"Buffer","data":[157,92,160,221,201,191,82,216,139,26,25,101,123,51,124,80,160,171,53,55]},"announce":[],"urlList":[]}}