{"title":"MiamiMeanGirls Carmela - Face Slaps to a little elf 1080p HD","uid":13060914,"size":793785532,"categoryP":"porn","categoryS":"hd___movies","magnet":"?xt=urn:btih:ae79e934a3db2136f570e41e6a3ff555be3f00ce&amp;dn=MiamiMeanGirls+Carmela+-+Face+Slaps+to+a+little+elf+1080p+HD&amp;tr=udp%3A%2F%2Ftracker.leechers-paradise.org%3A6969&amp;tr=udp%3A%2F%2Fzer0day.ch%3A1337&amp;tr=udp%3A%2F%2Fopen.demonii.com%3A1337&amp;tr=udp%3A%2F%2Ftracker.coppersurfer.tk%3A6969&amp;tr=udp%3A%2F%2Fexodus.desync.com%3A6969","seeders":1,"leechers":1,"uploader":"mdemeo73","files":1,"time":1450713876,"description":"MiamiMeanGirls Carmela - Face Slaps to a little elf 1080p HD\r\nSize: 793785532 bytes (757.01 MiB), duration: 00:08:40, avg.bitrate: 12212 kb/s\r\nAudio: aac, 48000 Hz, stereo (eng)\r\nVideo: h264, yuv420p, 1920x1080, 59.94 fps(r) (eng)\r\n\r\n\r\n\r\nView Screen\r\n \nhttp://thumbnailus.com/img-5677d5e077ffd.html","torrent":{"xt":"urn:btih:ae79e934a3db2136f570e41e6a3ff555be3f00ce","amp;dn":"MiamiMeanGirls+Carmela+-+Face+Slaps+to+a+little+elf+1080p+HD","amp;tr":["udp%3A%2F%2Ftracker.leechers-paradise.org%3A6969","udp%3A%2F%2Fzer0day.ch%3A1337","udp%3A%2F%2Fopen.demonii.com%3A1337","udp%3A%2F%2Ftracker.coppersurfer.tk%3A6969","udp%3A%2F%2Fexodus.desync.com%3A6969"],"infoHash":"ae79e934a3db2136f570e41e6a3ff555be3f00ce","infoHashBuffer":{"type":"Buffer","data":[174,121,233,52,163,219,33,54,245,112,228,30,106,63,245,85,190,63,0,206]},"announce":[],"urlList":[]}}