{"title":"Happy.Endings.S03E12.HDTV.XviD-AFG","uid":8078129,"size":186048955,"categoryP":"video","categoryS":"tv_shows","magnet":"?xt=urn:btih:b85904ae988df8abee8a9c96bdb415f613ec7c59&amp;dn=Happy.Endings.S03E12.HDTV.XviD-AFG&amp;tr=udp%3A%2F%2Ftracker.openbittorrent.com%3A80&amp;tr=udp%3A%2F%2Fopen.demonii.com%3A1337&amp;tr=udp%3A%2F%2Ftracker.coppersurfer.tk%3A6969&amp;tr=udp%3A%2F%2Fexodus.desync.com%3A6969","seeders":1,"leechers":0,"uploader":"TvTeam","files":4,"time":1359430239,"description":"::::::::::::::::::::::::::::::::::::::::::::::::::::::::::::::::::::::::::\n  &lt;a href=&quot;\nhttp://www.torrenting.com&quot; rel=&quot;nofollow&quot; target=&quot;_NEW&quot;&gt;\nhttp://www.torrenting.com&lt;/a&gt;  : TOP MOVIE TORRENT SITE -  Sign up is OPEN for now!\n\n::::::::::::::::::::::::::::::::::::::::::::::::::::::::::::::::::::::::::\n\n(((((((((((((= Enjoy No RAR releases =))))))))))))))))))))\n\n\n...................................NFO:....................................\n\nEnjoy our Fast Upload.\nFor more info about this release, open .NFO file with notepad !!!\n\n-------------------------------------------------------------------------------------\n\n\nMust Try:  &lt;a href=&quot; http://www.torrenting.com&quot; rel=&quot;nofollow&quot; target=&quot;_NEW&quot;&gt; http://www.torrenting.com&lt;/a&gt;\n\nVisit it, Sit back, enjoy. I am sure you'll like it.","torrent":{"xt":"urn:btih:b85904ae988df8abee8a9c96bdb415f613ec7c59","amp;dn":"Happy.Endings.S03E12.HDTV.XviD-AFG","amp;tr":["udp%3A%2F%2Ftracker.openbittorrent.com%3A80","udp%3A%2F%2Fopen.demonii.com%3A1337","udp%3A%2F%2Ftracker.coppersurfer.tk%3A6969","udp%3A%2F%2Fexodus.desync.com%3A6969"],"infoHash":"b85904ae988df8abee8a9c96bdb415f613ec7c59","infoHashBuffer":{"type":"Buffer","data":[184,89,4,174,152,141,248,171,238,138,156,150,189,180,21,246,19,236,124,89]},"announce":[],"urlList":[]}}