{"title":"MMV Films German mature housewife fucked","uid":15835954,"size":132340180,"categoryP":"porn","categoryS":"movie_clips","magnet":"?xt=urn:btih:ca7d311f0674d9660a520d00f1a8d600e874053e&amp;dn=MMV+Films+German+mature+housewife+fucked&amp;tr=udp%3A%2F%2Ftracker.leechers-paradise.org%3A6969&amp;tr=udp%3A%2F%2Fzer0day.ch%3A1337&amp;tr=udp%3A%2F%2Fopen.demonii.com%3A1337&amp;tr=udp%3A%2F%2Ftracker.coppersurfer.tk%3A6969&amp;tr=udp%3A%2F%2Fexodus.desync.com%3A6969","seeders":1,"leechers":0,"uploader":"demonoidt","files":1,"time":1473973433,"description":"Samples\r\n \nhttp://adultwallpapers.co.in/mmv-films-german-mature-housewife-fucked/\r\n \nhttp://demonoid.co/2016/09/15/mmv-films-german-mature-housewife-fucked/","torrent":{"xt":"urn:btih:ca7d311f0674d9660a520d00f1a8d600e874053e","amp;dn":"MMV+Films+German+mature+housewife+fucked","amp;tr":["udp%3A%2F%2Ftracker.leechers-paradise.org%3A6969","udp%3A%2F%2Fzer0day.ch%3A1337","udp%3A%2F%2Fopen.demonii.com%3A1337","udp%3A%2F%2Ftracker.coppersurfer.tk%3A6969","udp%3A%2F%2Fexodus.desync.com%3A6969"],"infoHash":"ca7d311f0674d9660a520d00f1a8d600e874053e","infoHashBuffer":{"type":"Buffer","data":[202,125,49,31,6,116,217,102,10,82,13,0,241,168,214,0,232,116,5,62]},"announce":[],"urlList":[]}}