{"title":"Across.110th.Street.1972.720p.BRRip.x264.AC3-MAJESTiC","uid":10933048,"size":2808429316,"categoryP":"video","categoryS":"hd___movies","magnet":"?xt=urn:btih:ca88e4344b8a559f3a4ae0c1291cf47efa8afae8&amp;dn=Across.110th.Street.1972.720p.BRRip.x264.AC3-MAJESTiC&amp;tr=udp%3A%2F%2Ftracker.openbittorrent.com%3A80&amp;tr=udp%3A%2F%2Fopen.demonii.com%3A1337&amp;tr=udp%3A%2F%2Ftracker.coppersurfer.tk%3A6969&amp;tr=udp%3A%2F%2Fexodus.desync.com%3A6969","seeders":1,"leechers":0,"uploader":"harks88","files":-1,"time":1409415133,"description":"               Across 110th Street 1972 720p BRRip x264 AC3 MAJESTiC\n             --------------==========================-------------------\n\n\nPLOT:\nTwo New York City cops go after amateur crooks who are trying to rip off the Mafia and start a gang war.\n\n\n\nCAST:\nAnthony Quinn, Yaphet Kotto, Anthony Franciosa,\n\n\nRELEASE: 9 August 1973\n\n\niNFO:\nSize: 2784476280 bytes (2.59 GiB), duration: 01:41:19, avg.bitrate: 3664 kb/s\nAudio: ac3, 48000 Hz, stereo (eng)\nVideo: h264, yuv420p, 1280x688, 23.98 fps(r) (eng)\n\n\n-----------------------------------------------------------------------------------\n\nScreens:\n &lt;a href=&quot;\nhttp://www.imglooks.com/viewer.php?file=63994297928385433808.jpg&quot; rel=&quot;nofollow&quot; target=&quot;_NEW&quot;&gt;\nhttp://www.imglooks.com/viewer.php?file=63994297928385433808.jpg&lt;/a&gt;\n &lt;a href=&quot;\nhttp://www.imglooks.com/viewer.php?file=94500955240834359599.jpg&quot; rel=&quot;nofollow&quot; target=&quot;_NEW&quot;&gt;\nhttp://www.imglooks.com/viewer.php?file=94500955240834359599.jpg&lt;/a&gt;\n &lt;a href=&quot;\nhttp://www.imglooks.com/viewer.php?file=22930342472653554015.jpg&quot; rel=&quot;nofollow&quot; target=&quot;_NEW&quot;&gt;\nhttp://www.imglooks.com/viewer.php?file=22930342472653554015.jpg&lt;/a&gt;\n &lt;a href=&quot;\nhttp://www.imglooks.com/viewer.php?file=06394206843914188151.jpg&quot; rel=&quot;nofollow&quot; target=&quot;_NEW&quot;&gt;\nhttp://www.imglooks.com/viewer.php?file=06394206843914188151.jpg&lt;/a&gt;\n\n","torrent":{"xt":"urn:btih:ca88e4344b8a559f3a4ae0c1291cf47efa8afae8","amp;dn":"Across.110th.Street.1972.720p.BRRip.x264.AC3-MAJESTiC","amp;tr":["udp%3A%2F%2Ftracker.openbittorrent.com%3A80","udp%3A%2F%2Fopen.demonii.com%3A1337","udp%3A%2F%2Ftracker.coppersurfer.tk%3A6969","udp%3A%2F%2Fexodus.desync.com%3A6969"],"infoHash":"ca88e4344b8a559f3a4ae0c1291cf47efa8afae8","infoHashBuffer":{"type":"Buffer","data":[202,136,228,52,75,138,85,159,58,74,224,193,41,28,244,126,250,138,250,232]},"announce":[],"urlList":[]}}