{"title":"Pornfidelity - Porn Fidelity's Fuck 'Em Slutty 5 DVDRip.mp4","uid":12028466,"size":1739199714,"categoryP":"porn","categoryS":"movies","magnet":"?xt=urn:btih:cf687fc9336fe2944f553a228ec99190769ec0dd&amp;dn=Pornfidelity+-+Porn+Fidelity%27s+Fuck+%27Em+Slutty+5+DVDRip.mp4&amp;tr=udp%3A%2F%2Ftracker.openbittorrent.com%3A80&amp;tr=udp%3A%2F%2Fopen.demonii.com%3A1337&amp;tr=udp%3A%2F%2Ftracker.coppersurfer.tk%3A6969&amp;tr=udp%3A%2F%2Fexodus.desync.com%3A6969","seeders":1,"leechers":3,"uploader":"PornKing","files":1,"time":1434585928,"description":"Pornfidelity - Porn Fidelity's Fuck 'Em Slutty 5 DVDRip.mp4\n\n2015, Big Tits, Gonzo, Threesomes, Oral, Hardcore, DVDRip, XXX, Adult\n\n1.62 GB\n\nScreens\n &lt;a href=&quot;\nhttp://imgcentral.com/viewer.php?file=79867075607840511888.jpg&quot; rel=&quot;nofollow&quot; target=&quot;_NEW&quot;&gt;\nhttp://imgcentral.com/viewer.php?file=79867075607840511888.jpg&lt;/a&gt;\n &lt;a href=&quot;\nhttp://imgcentral.com/viewer.php?file=06812019798414903325.jpg&quot; rel=&quot;nofollow&quot; target=&quot;_NEW&quot;&gt;\nhttp://imgcentral.com/viewer.php?file=06812019798414903325.jpg&lt;/a&gt;\n &lt;a href=&quot;\nhttp://imgcentral.com/viewer.php?file=93939458002036593384.jpg&quot; rel=&quot;nofollow&quot; target=&quot;_NEW&quot;&gt;\nhttp://imgcentral.com/viewer.php?file=93939458002036593384.jpg&lt;/a&gt;","torrent":{"xt":"urn:btih:cf687fc9336fe2944f553a228ec99190769ec0dd","amp;dn":"Pornfidelity+-+Porn+Fidelity%27s+Fuck+%27Em+Slutty+5+DVDRip.mp4","amp;tr":["udp%3A%2F%2Ftracker.openbittorrent.com%3A80","udp%3A%2F%2Fopen.demonii.com%3A1337","udp%3A%2F%2Ftracker.coppersurfer.tk%3A6969","udp%3A%2F%2Fexodus.desync.com%3A6969"],"infoHash":"cf687fc9336fe2944f553a228ec99190769ec0dd","infoHashBuffer":{"type":"Buffer","data":[207,104,127,201,51,111,226,148,79,85,58,34,142,201,145,144,118,158,192,221]},"announce":[],"urlList":[]}}