{"title":"[MilfHunter] - Ginger Allen - Juicy ginger [RealityKings] 27 APR","uid":11853366,"size":346189434,"categoryP":"porn","categoryS":"movie_clips","magnet":"?xt=urn:btih:d2170d209bd4859d54181647f2dfaf4ff372e529&amp;dn=%5BMilfHunter%5D+-+Ginger+Allen+-+Juicy+ginger+%5BRealityKings%5D+27+APR&amp;tr=udp%3A%2F%2Ftracker.openbittorrent.com%3A80&amp;tr=udp%3A%2F%2Fopen.demonii.com%3A1337&amp;tr=udp%3A%2F%2Ftracker.coppersurfer.tk%3A6969&amp;tr=udp%3A%2F%2Fexodus.desync.com%3A6969","seeders":1,"leechers":5,"uploader":"manam69","files":1,"time":1430129257,"description":"[MilfHunter] - Ginger Allen - Juicy ginger [RealityKings] - NEW 27 APRIL 2015 NEW\n\nGinger had a business proposition for Levi, the MILF hunter. She was born in Europe, had lived in the States all her life, but now, for some crazy reason, she needed a green card to stay. Since Ginger was a sexy MILF, she thought maybe Levi would marry her so she could stay in the country. She figured she was an amazing lay and was sexy as hell, so why wouldn't he? They discussed the situation a little, but Levi had to try out the goods first. Ginger had PLENTY of goods. Not many dudes would pass on Ginger, but after fucking this hot MILF, Levi had yet to decide\n &lt;a href=&quot;\nhttp://s20.postimg.org/4xvl2l35p/gingerall2.jpg&quot; rel=&quot;nofollow&quot; target=&quot;_NEW&quot;&gt;\nhttp://s20.postimg.org/4xvl2l35p/gingerall2.jpg&lt;/a&gt;\n &lt;a href=&quot;\nhttp://s20.postimg.org/yefsiqywt/juicy_ginger_big.jpg&quot; rel=&quot;nofollow&quot; target=&quot;_NEW&quot;&gt;\nhttp://s20.postimg.org/yefsiqywt/juicy_ginger_big.jpg&lt;/a&gt;","torrent":{"xt":"urn:btih:d2170d209bd4859d54181647f2dfaf4ff372e529","amp;dn":"%5BMilfHunter%5D+-+Ginger+Allen+-+Juicy+ginger+%5BRealityKings%5D+27+APR","amp;tr":["udp%3A%2F%2Ftracker.openbittorrent.com%3A80","udp%3A%2F%2Fopen.demonii.com%3A1337","udp%3A%2F%2Ftracker.coppersurfer.tk%3A6969","udp%3A%2F%2Fexodus.desync.com%3A6969"],"infoHash":"d2170d209bd4859d54181647f2dfaf4ff372e529","infoHashBuffer":{"type":"Buffer","data":[210,23,13,32,155,212,133,157,84,24,22,71,242,223,175,79,243,114,229,41]},"announce":[],"urlList":[]}}