{"title":"Hot Shit! - Laser Attack (Original Mix)","uid":9502259,"size":11584559,"categoryP":"audio","categoryS":"music","magnet":"?xt=urn:btih:db997dea966f58c69dcca3e5b9b2b30e18f1d5b5&amp;dn=Hot+Shit%21+-+Laser+Attack+%28Original+Mix%29&amp;tr=udp%3A%2F%2Ftracker.openbittorrent.com%3A80&amp;tr=udp%3A%2F%2Fopen.demonii.com%3A1337&amp;tr=udp%3A%2F%2Ftracker.coppersurfer.tk%3A6969&amp;tr=udp%3A%2F%2Fexodus.desync.com%3A6969","seeders":1,"leechers":0,"uploader":"yeahsx","files":-1,"time":1390246859,"description":"Label: Digital Complex Records\nArtist: Hot Shit!\nAudio Bit Rate: 320 Kbps\nDuration: 04:48 min\nBPM: 130\nGenre: Electro House\nCatalog # DCE0063\nCover: Yes\nFormat/Codec: .mp3","torrent":{"xt":"urn:btih:db997dea966f58c69dcca3e5b9b2b30e18f1d5b5","amp;dn":"Hot+Shit%21+-+Laser+Attack+%28Original+Mix%29","amp;tr":["udp%3A%2F%2Ftracker.openbittorrent.com%3A80","udp%3A%2F%2Fopen.demonii.com%3A1337","udp%3A%2F%2Ftracker.coppersurfer.tk%3A6969","udp%3A%2F%2Fexodus.desync.com%3A6969"],"infoHash":"db997dea966f58c69dcca3e5b9b2b30e18f1d5b5","infoHashBuffer":{"type":"Buffer","data":[219,153,125,234,150,111,88,198,157,204,163,229,185,178,179,14,24,241,213,181]},"announce":[],"urlList":[]}}