{"title":"Penthouse - Nicole Aniston (Hidden Camera 3 Screwtown) [720p]","uid":9047864,"size":682593535,"categoryP":"porn","categoryS":"other","magnet":"?xt=urn:btih:ecb3fa59717bd62e1c2025d62ad230cacdca0e52&amp;dn=Penthouse+-+Nicole+Aniston+%28Hidden+Camera+3+Screwtown%29+%5B720p%5D&amp;tr=udp%3A%2F%2Ftracker.openbittorrent.com%3A80&amp;tr=udp%3A%2F%2Fopen.demonii.com%3A1337&amp;tr=udp%3A%2F%2Ftracker.coppersurfer.tk%3A6969&amp;tr=udp%3A%2F%2Fexodus.desync.com%3A6969","seeders":1,"leechers":1,"uploader":"R0thschild","files":2,"time":1381797469,"description":"Screens: &lt;a href=&quot;\nhttp://imgtou.com/?v=110758&quot; rel=&quot;nofollow&quot; target=&quot;_NEW&quot;&gt;\nhttp://imgtou.com/?v=110758&lt;/a&gt; &lt;a href=&quot;\nhttp://imgtou.com/?v=812412&quot; rel=&quot;nofollow&quot; target=&quot;_NEW&quot;&gt;\nhttp://imgtou.com/?v=812412&lt;/a&gt;\n\nMore at  &lt;a href=&quot;\nhttp://piratebg.com&quot; rel=&quot;nofollow&quot; target=&quot;_NEW&quot;&gt;\nhttp://piratebg.com&lt;/a&gt;","torrent":{"xt":"urn:btih:ecb3fa59717bd62e1c2025d62ad230cacdca0e52","amp;dn":"Penthouse+-+Nicole+Aniston+%28Hidden+Camera+3+Screwtown%29+%5B720p%5D","amp;tr":["udp%3A%2F%2Ftracker.openbittorrent.com%3A80","udp%3A%2F%2Fopen.demonii.com%3A1337","udp%3A%2F%2Ftracker.coppersurfer.tk%3A6969","udp%3A%2F%2Fexodus.desync.com%3A6969"],"infoHash":"ecb3fa59717bd62e1c2025d62ad230cacdca0e52","infoHashBuffer":{"type":"Buffer","data":[236,179,250,89,113,123,214,46,28,32,37,214,42,210,48,202,205,202,14,82]},"announce":[],"urlList":[]}}