{"title":"The Bold And The Beautiful - S27 Ep6929 - 2014-10-10","uid":11190584,"size":320905173,"categoryP":"video","categoryS":"tv_shows","magnet":"?xt=urn:btih:f163098de2fa3cb51216500bd865f3232c5e0770&amp;dn=The+Bold+And+The+Beautiful+-+S27+Ep6929+-+2014-10-10&amp;tr=udp%3A%2F%2Ftracker.openbittorrent.com%3A80&amp;tr=udp%3A%2F%2Fopen.demonii.com%3A1337&amp;tr=udp%3A%2F%2Ftracker.coppersurfer.tk%3A6969&amp;tr=udp%3A%2F%2Fexodus.desync.com%3A6969","seeders":1,"leechers":1,"uploader":"gurfel65","files":4,"time":1412987060,"description":"Bill and Katie find themselves having a real conversation about their present... and their past.","torrent":{"xt":"urn:btih:f163098de2fa3cb51216500bd865f3232c5e0770","amp;dn":"The+Bold+And+The+Beautiful+-+S27+Ep6929+-+2014-10-10","amp;tr":["udp%3A%2F%2Ftracker.openbittorrent.com%3A80","udp%3A%2F%2Fopen.demonii.com%3A1337","udp%3A%2F%2Ftracker.coppersurfer.tk%3A6969","udp%3A%2F%2Fexodus.desync.com%3A6969"],"infoHash":"f163098de2fa3cb51216500bd865f3232c5e0770","infoHashBuffer":{"type":"Buffer","data":[241,99,9,141,226,250,60,181,18,22,80,11,216,101,243,35,44,94,7,112]},"announce":[],"urlList":[]}}