{"title":"Vikings.S02E08.HDTV.x264-KILLERS","uid":9987895,"size":373113705,"categoryP":"video","categoryS":"tv_shows","magnet":"?xt=urn:btih:f1d3a9493e54c38ff65c625fe07f6a15fe776920&amp;dn=Vikings.S02E08.HDTV.x264-KILLERS&amp;tr=udp%3A%2F%2Ftracker.openbittorrent.com%3A80&amp;tr=udp%3A%2F%2Fopen.demonii.com%3A1337&amp;tr=udp%3A%2F%2Ftracker.coppersurfer.tk%3A6969&amp;tr=udp%3A%2F%2Fexodus.desync.com%3A6969","seeders":1,"leechers":0,"uploader":"TvTeam","files":4,"time":1397810738,"description":"::::::::::::::::::::::::::::::::::::::::::::::::::::::::::::::::::::::::::\n  &lt;a href=&quot;\nhttp://www.torrenting.com&quot; rel=&quot;nofollow&quot; target=&quot;_NEW&quot;&gt;\nhttp://www.torrenting.com&lt;/a&gt;\n\nEver Experianced a perfect Scene torrent site?\n\n\n\nGive it a try: http://www.torrenting.com\n\n\n\nYou will not regret.\n\nSign up is free and open !!!\n\n\n::::::::::::::::::::::::::::::::::::::::::::::::::::::::::::::::::::::::::\n\n(= Enjoy No RAR releases =)","torrent":{"xt":"urn:btih:f1d3a9493e54c38ff65c625fe07f6a15fe776920","amp;dn":"Vikings.S02E08.HDTV.x264-KILLERS","amp;tr":["udp%3A%2F%2Ftracker.openbittorrent.com%3A80","udp%3A%2F%2Fopen.demonii.com%3A1337","udp%3A%2F%2Ftracker.coppersurfer.tk%3A6969","udp%3A%2F%2Fexodus.desync.com%3A6969"],"infoHash":"f1d3a9493e54c38ff65c625fe07f6a15fe776920","infoHashBuffer":{"type":"Buffer","data":[241,211,169,73,62,84,195,143,246,92,98,95,224,127,106,21,254,119,105,32]},"announce":[],"urlList":[]}}